{
  "id": "3590251",
  "name": "travel",
  "font_family": "iconfont",
  "css_prefix_text": "icon-",
  "description": "",
  "glyphs": [
    {
      "icon_id": "76992",
      "name": "搜索",
      "font_class": "sousuo",
      "unicode": "e600",
      "unicode_decimal": 58880
    },
    {
      "icon_id": "1718353",
      "name": "下箭头",
      "font_class": "xiajiantou",
      "unicode": "e601",
      "unicode_decimal": 58881
    },
    {
      "icon_id": "15838561",
      "name": "arrow-left-bold",
      "font_class": "arrow-left-bold",
      "unicode": "e685",
      "unicode_decimal": 59013
    }
  ]
}
